om/__init__.py
om/config.py
om/executor.py
om/handler.py
om/metrics.py
om/supervisor.py
om/utils/__init__.py
om/utils/logger.py
om-0.0.1.data/scripts/om
om-0.0.1.dist-info/DESCRIPTION.rst
om-0.0.1.dist-info/METADATA
om-0.0.1.dist-info/metadata.json
om-0.0.1.dist-info/RECORD
om-0.0.1.dist-info/top_level.txt
om-0.0.1.dist-info/WHEEL
