Metadata-Version: 2.0
Name: om
Version: 0.0.1
Summary: Collect usage for remote boxes without configuration.
Home-page: http://github.com/overseer-monitoring/om
Author: Andre Dieb Martins, Thiago Sousa Santos
Author-email: andre.dieb@gmail.com, thiagossantos@gmail.com
License: LGPL
Platform: UNKNOWN
Classifier: Development Status :: 2 - Pre-Alpha
Classifier: Intended Audience :: Developers
Classifier: Intended Audience :: System Administrators
Classifier: Natural Language :: English
Classifier: License :: OSI Approved :: GNU Lesser General Public License v3 (LGPLv3)
Classifier: Programming Language :: Python
Classifier: Programming Language :: Python :: 2.6
Classifier: Programming Language :: Python :: 2.7
Classifier: Programming Language :: Python :: 3
Classifier: Programming Language :: Python :: 3.3
Requires-Dist: paramiko
